odoo/addons/l10n_nl_postcode/README.rst
odoo/addons/l10n_nl_postcode/__init__.py
odoo/addons/l10n_nl_postcode/__manifest__.py
odoo/addons/l10n_nl_postcode/i18n/l10n_nl_postcode.pot
odoo/addons/l10n_nl_postcode/i18n/nl.po
odoo/addons/l10n_nl_postcode/models/__init__.py
odoo/addons/l10n_nl_postcode/models/res_partner.py
odoo/addons/l10n_nl_postcode/readme/CONTRIBUTORS.md
odoo/addons/l10n_nl_postcode/readme/DESCRIPTION.md
odoo/addons/l10n_nl_postcode/readme/USAGE.md
odoo/addons/l10n_nl_postcode/static/description/icon.png
odoo/addons/l10n_nl_postcode/static/description/index.html
odoo/addons/l10n_nl_postcode/tests/__init__.py
odoo/addons/l10n_nl_postcode/tests/test_l10n_nl_postcode.py
odoo_addon_l10n_nl_postcode-18.0.1.0.0.2.dist-info/METADATA
odoo_addon_l10n_nl_postcode-18.0.1.0.0.2.dist-info/WHEEL
odoo_addon_l10n_nl_postcode-18.0.1.0.0.2.dist-info/top_level.txt
odoo_addon_l10n_nl_postcode-18.0.1.0.0.2.dist-info/RECORD
